pcds/__init__.py
pcds/bstree.py
pcds/clinkedlist.py
pcds/dlinkedlist.py
pcds/encrypt.py
pcds/linkedlist.py
pcds/pqueue.py
pcds/queue.py
pcds/set.py
pcds/stack.py
pcds/utilities.py
pcds-1.1.2.data/data/LICENSE
tests/__init__.py
tests/test_bstree.py
tests/test_clinkedlist.py
tests/test_dlinkedlist.py
tests/test_encrypt.py
tests/test_linkedlist.py
tests/test_pqueue.py
tests/test_queue.py
tests/test_set.py
tests/test_stack.py
tests/test_utilities.py
tests/pcds/__init__.py
tests/pcds/bstree.py
tests/pcds/clinkedlist.py
tests/pcds/dlinkedlist.py
tests/pcds/encrypt.py
tests/pcds/linkedlist.py
tests/pcds/pqueue.py
tests/pcds/queue.py
tests/pcds/set.py
tests/pcds/stack.py
tests/pcds/utilities.py
pcds-1.1.2.dist-info/LICENSE
pcds-1.1.2.dist-info/METADATA
pcds-1.1.2.dist-info/WHEEL
pcds-1.1.2.dist-info/top_level.txt
pcds-1.1.2.dist-info/RECORD
