Metadata-Version: 2.1
Name: pcds
Version: 1.1.2
Summary: This python package creates and manages the common data structures like queue, priority queue, stack, linkedlist, circular linkedlist, binary tree, set etc. Supported data types are int, float, str, bool, NoneType, list, tuple, and dictionary.
Home-page: 
Author: A K M Aminul Islam
Author-email: aminul71bd@gmail.com
License: NEWTONIA FREEWARE LICENSE
License-File: LICENSE
Requires-Dist: upmath >=2.0.0
